[
    {
        "timestamp": "2026-06-16T19:34:56.843Z",
        "step": "init",
        "status": "success",
        "details": "Risk level: medium"
    },
    {
        "timestamp": "2026-06-16T19:34:56.846Z",
        "step": "planning",
        "status": "started",
        "details": ""
    },
    {
        "timestamp": "2026-06-16T19:34:56.847Z",
        "step": "planning",
        "status": "success",
        "details": "Retrieved existing plan"
    },
    {
        "timestamp": "2026-06-16T19:34:56.849Z",
        "step": "plan-reviewing",
        "status": "started",
        "details": ""
    },
    {
        "timestamp": "2026-06-16T19:34:56.850Z",
        "step": "plan-reviewing",
        "status": "success",
        "details": "Plan validated successfully"
    },
    {
        "timestamp": "2026-06-16T19:34:56.852Z",
        "step": "developing",
        "status": "started",
        "details": ""
    },
    {
        "timestamp": "2026-06-16T19:34:56.942Z",
        "step": "developing",
        "status": "success",
        "details": "Workspace code changes detected"
    },
    {
        "timestamp": "2026-06-16T19:34:56.944Z",
        "step": "code-reviewing",
        "status": "started",
        "details": ""
    },
    {
        "timestamp": "2026-06-16T19:34:57.087Z",
        "step": "code-reviewing",
        "status": "success",
        "details": "Syntax validation passed"
    },
    {
        "timestamp": "2026-06-16T19:34:57.089Z",
        "step": "testing",
        "status": "started",
        "details": ""
    },
    {
        "timestamp": "2026-06-16T19:34:58.055Z",
        "step": "testing",
        "status": "success",
        "details": "All build checks and tests passed"
    },
    {
        "timestamp": "2026-06-16T19:40:30.180Z",
        "step": "init",
        "status": "success",
        "details": "Risk level: medium"
    },
    {
        "timestamp": "2026-06-16T19:40:30.183Z",
        "step": "planning",
        "status": "started",
        "details": ""
    },
    {
        "timestamp": "2026-06-16T19:40:30.184Z",
        "step": "planning",
        "status": "success",
        "details": "Retrieved existing plan"
    },
    {
        "timestamp": "2026-06-16T19:40:30.186Z",
        "step": "plan-reviewing",
        "status": "started",
        "details": ""
    },
    {
        "timestamp": "2026-06-16T19:40:30.188Z",
        "step": "plan-reviewing",
        "status": "success",
        "details": "Plan validated successfully"
    },
    {
        "timestamp": "2026-06-16T19:40:30.190Z",
        "step": "developing",
        "status": "started",
        "details": ""
    },
    {
        "timestamp": "2026-06-16T19:40:30.272Z",
        "step": "developing",
        "status": "success",
        "details": "Workspace code changes detected"
    },
    {
        "timestamp": "2026-06-16T19:40:30.274Z",
        "step": "code-reviewing",
        "status": "started",
        "details": ""
    },
    {
        "timestamp": "2026-06-16T19:40:30.419Z",
        "step": "code-reviewing",
        "status": "success",
        "details": "Syntax validation passed"
    },
    {
        "timestamp": "2026-06-16T19:40:30.420Z",
        "step": "testing",
        "status": "started",
        "details": ""
    },
    {
        "timestamp": "2026-06-16T19:40:31.354Z",
        "step": "testing",
        "status": "success",
        "details": "All build checks and tests passed"
    }
]